dacc/__init__.py
dacc-0.0.2.dist-info/LICENSE
dacc-0.0.2.dist-info/METADATA
dacc-0.0.2.dist-info/WHEEL
dacc-0.0.2.dist-info/top_level.txt
dacc-0.0.2.dist-info/RECORD
