Metadata-Version: 2.1
Name: dacc
Version: 0.0.2
Summary: A declarative approache to data access object construction
Home-page: https://github.com/i2mint/dacc
Author: OtoSense
License: mit
Platform: any
